qurpc/__init__.py
qurpc/__main__.py
qurpc/_kcp.cp310-win_amd64.pyd
qurpc/bencoder.py
qurpc/client.py
qurpc/dht.py
qurpc/exceptions.py
qurpc/kad.py
qurpc/kcp.py
qurpc/rpc.py
qurpc/serialize.py
qurpc/server.py
qurpc/utils.py
qurpc/version.py
qurpc-2.2.8.dist-info/LICENSE
qurpc-2.2.8.dist-info/METADATA
qurpc-2.2.8.dist-info/WHEEL
qurpc-2.2.8.dist-info/entry_points.txt
qurpc-2.2.8.dist-info/top_level.txt
qurpc-2.2.8.dist-info/RECORD
